seer_pas_sdk/__init__.py
seer_pas_sdk/auth/__init__.py
seer_pas_sdk/auth/auth.py
seer_pas_sdk/common/__init__.py
seer_pas_sdk/common/errors.py
seer_pas_sdk/common/groupanalysis.py
seer_pas_sdk/core/__init__.py
seer_pas_sdk/core/sdk.py
seer_pas_sdk/core/unsupported.py
seer_pas_sdk/objects/__init__.py
seer_pas_sdk/objects/groupanalysis.py
seer_pas_sdk/objects/platemap.py
seer_pas_sdk/objects/volcanoplot.py
seer_pas_sdk-3.0.0.dist-info/licenses/LICENSE.txt
seer_pas_sdk-3.0.0.dist-info/METADATA
seer_pas_sdk-3.0.0.dist-info/WHEEL
seer_pas_sdk-3.0.0.dist-info/top_level.txt
seer_pas_sdk-3.0.0.dist-info/RECORD
