Metadata-Version: 2.4
Name: seer-pas-sdk
Version: 3.0.0
Summary: SDK for Seer Proteograph Analysis Suite (PAS)
Author-email: Ryan Sun <rsun@seer.bio>
License: 
Project-URL: Issues, https://github.com/seerbio/seer-pas-sdk/issues
Keywords: seer,sdk,pas,mass spectrometry,proteomics
Classifier: Development Status :: 4 - Beta
Classifier: Topic :: Scientific/Engineering :: Bio-Informatics
Classifier: Operating System :: OS Independent
Classifier: Programming Language :: Python :: 3
Classifier: Programming Language :: Python :: 3 :: Only
Requires-Python: >=3.8
License-File: LICENSE.txt
Requires-Dist: boto3>=1.26.152
Requires-Dist: botocore>=1.29.152
Requires-Dist: pandas>=2.0.1
Requires-Dist: numpy<2.0.0,>=1.5.3
Requires-Dist: PyJWT>=2.8.0
Requires-Dist: python-dotenv>=1.0.0
Requires-Dist: Requests>=2.31.0
Requires-Dist: tqdm>=4.65.0
Requires-Dist: deprecation
Dynamic: license-file
